tools21cm/Friends_of_Friends.py
tools21cm/ViteBetti.py
tools21cm/ViteBetti_cython.cpp
tools21cm/ViteBetti_cython.cpython-310-darwin.so
tools21cm/ViteBetti_cython.cpython-311-darwin.so
tools21cm/ViteBetti_cython.pyx
tools21cm/ViteBetti_numba.py
tools21cm/__init__.py
tools21cm/angular_coordinates.py
tools21cm/apply_mpi_lya_c.py
tools21cm/astro_tools.py
tools21cm/beam_convolve.py
tools21cm/bispectrum.py
tools21cm/box_counting.py
tools21cm/bubble_stats.py
tools21cm/compare_constraints.py
tools21cm/const.py
tools21cm/conv.py
tools21cm/corr_function.py
tools21cm/cosmo.py
tools21cm/density_file.py
tools21cm/deprecated.py
tools21cm/fitting_methods.py
tools21cm/foreground_model.py
tools21cm/gaussian_random_field.py
tools21cm/halo_list.py
tools21cm/helper_functions.py
tools21cm/identify_regions.py
tools21cm/irate_file.py
tools21cm/lightcone.py
tools21cm/line_intensity.py
tools21cm/lyman_alpha_coupling.py
tools21cm/lyman_alpha_transmission.py
tools21cm/mfp_np.py
tools21cm/model_21cmfast.py
tools21cm/morph.py
tools21cm/nbody_file.py
tools21cm/nbody_pkdgrav.py
tools21cm/nbody_tools.py
tools21cm/noise_model.py
tools21cm/numba_functions.py
tools21cm/percolation.py
tools21cm/plotting.py
tools21cm/position_dependent_power_spectrum.py
tools21cm/power_legendre.py
tools21cm/power_spect_fast.py
tools21cm/power_spectrum.py
tools21cm/power_spectrum_noise.py
tools21cm/primary_beam.py
tools21cm/pv_mpm.py
tools21cm/radio_data_calibration.py
tools21cm/radio_telescope_calibration.py
tools21cm/radio_telescope_layout.py
tools21cm/radio_telescope_noise.py
tools21cm/radio_telescope_rotation.py
tools21cm/radio_telescope_sensitivity.py
tools21cm/read_files.py
tools21cm/scipy_func.py
tools21cm/segmentation.py
tools21cm/smoothing.py
tools21cm/source_file.py
tools21cm/spa_np.py
tools21cm/statistics.py
tools21cm/superpixels.py
tools21cm/tau.py
tools21cm/telescope_functions.py
tools21cm/temper_file.py
tools21cm/temperature.py
tools21cm/test_case.py
tools21cm/topology.py
tools21cm/usefuls.py
tools21cm-2.3.8.dist-info/LICENSE.md
tools21cm-2.3.8.dist-info/METADATA
tools21cm-2.3.8.dist-info/WHEEL
tools21cm-2.3.8.dist-info/top_level.txt
tools21cm-2.3.8.dist-info/RECORD
