Metadata-Version: 2.1
Name: tools21cm
Version: 2.3.8
Author: Sambit Giri
Author-email: sambit.giri@gmail.com
License-File: LICENSE.md
Requires-Dist: cython
Requires-Dist: numpy
Requires-Dist: scipy
Requires-Dist: matplotlib
Requires-Dist: astropy
Requires-Dist: scikit-learn
Requires-Dist: scikit-image
Requires-Dist: tqdm
Requires-Dist: joblib
Requires-Dist: pandas
Requires-Dist: openpyxl
Requires-Dist: pytest
